gtd.py
todo/__init__.py
todo/card.py
todo/configuration.py
todo/connection.py
todo/display.py
todo/exceptions.py
todo/input.py
todo/misc.py
gtd.py-0.7.1.dist-info/LICENSE
gtd.py-0.7.1.dist-info/METADATA
gtd.py-0.7.1.dist-info/WHEEL
gtd.py-0.7.1.dist-info/entry_points.txt
gtd.py-0.7.1.dist-info/top_level.txt
gtd.py-0.7.1.dist-info/RECORD
