Metadata-Version: 2.1
Name: gtd.py
Version: 0.7.1
Summary: A Fast Command-line Interface for Trello
Home-page: https://github.com/delucks/gtd.py
Author: James Luck
Author-email: me@jamesluck.com
License: BSD 3-clause
Download-URL: https://github.com/delucks/gtd.py/tarball/0.7.1
Keywords: productivity,cli,trello,gtd,getting things done
Platform: UNKNOWN
Classifier: Development Status :: 4 - Beta
Classifier: Environment :: Console
Classifier: Intended Audience :: Developers
Classifier: Intended Audience :: System Administrators
Classifier: Intended Audience :: End Users/Desktop
Classifier: License :: OSI Approved :: BSD License
Classifier: Natural Language :: English
Classifier: Operating System :: MacOS :: MacOS X
Classifier: Operating System :: POSIX :: Linux
Classifier: Operating System :: POSIX :: BSD
Classifier: Programming Language :: Python :: 3 :: Only
Classifier: Topic :: Utilities
Requires-Python: >=3.8
Requires-Dist: PyYAML (==3.13)
Requires-Dist: py-trello (==0.15.0)
Requires-Dist: click (==7.0)
Requires-Dist: prompt-toolkit (==3.0.3)
Requires-Dist: prettytable (==0.7.2)
Requires-Dist: arrow (==0.12.1)
